elastic_apm_falcon/__init__.py
elastic_apm_falcon/utils.py
elastic_apm_falcon-1.0.1.dist-info/LICENSE
elastic_apm_falcon-1.0.1.dist-info/WHEEL
elastic_apm_falcon-1.0.1.dist-info/METADATA
elastic_apm_falcon-1.0.1.dist-info/RECORD
